bifeatureanalysis/RegressionLossFunc.py
bifeatureanalysis/__init__.py
bifeatureanalysis/aggregationfunc.py
bifeatureanalysis/templateproj.py
bifeatureanalysis-1.0.3.dist-info/LICENSE
bifeatureanalysis-1.0.3.dist-info/METADATA
bifeatureanalysis-1.0.3.dist-info/WHEEL
bifeatureanalysis-1.0.3.dist-info/top_level.txt
bifeatureanalysis-1.0.3.dist-info/RECORD
